{
  "name": "alipay",
  "title": "支付宝支付",
  "version": "1.0.0",
  "description": "支付宝支付驱动（APP/H5/PC）",
  "author": "lyshop",
  "depends": [],
  "menus": [],
  "permissions": [],
  "config_items": [
    { "key": "app_id", "label": "AppID", "type": "text", "required": true },
    { "key": "private_key", "label": "应用私钥", "type": "password", "required": true },
    { "key": "public_key", "label": "支付宝公钥", "type": "password", "required": true },
    { "key": "sandbox", "label": "沙箱模式", "type": "switch" },
    { "key": "notify_url", "label": "异步回调地址", "type": "text", "placeholder": "https://yourdomain.com/api/v1/notify/alipay" }
  ]
}
